{
  "title": "ரஷீத் கான்",
  "wikipediaUrl": "https://en.wikipedia.org/wiki/Rashid_Khan_(cricketer)",
  "coverImage": {
    "url": "-",
    "altText": "Image of ரஷீத் கான்"
  },
  "summary": "ரஷீத் கான் அர்மான், பொதுவாக ரஷீத் கான் என அறியப்படுகிறார், இவர் ஒரு ஆப்கானிஸ்தான் கிரிக்கெட் வீரர், அவர்களின் தேசிய அணிக்கு டி20 சர்வதேசப் போட்டிகளில் கேப்டனாக இருக்கிறார்.",
  "translations": [
    {
      "lang": "en",
      "title": "Rashid Khan",
      "url": "/read/en/rashid_khan"
    },
    {
      "lang": "hi",
      "title": "राशिद खान",
      "url": "/read/hi/rashid_khan"
    }
  ],
  "sections": [
    {
      "title": "விவரம்",
      "cardType": "table",
      "facts": [
        {
          "label": "முழுப் பெயர்",
          "value": {
            "label": "ரஷீத் கான் அர்மான்"
          }
        },
        {
          "label": "பிறந்த தேதி",
          "value": {
            "label": "Invalid Date (வயது 20)"
          }
        },
        {
          "label": "பிறந்த இடம்",
          "value": {
            "label": "நங்கர்ஹார், ஆப்கானிஸ்தான்",
            "url": "https://en.wikipedia.org/wiki/Nangarhar_Province",
            "contentUrl": "/static/content/ta/bogra.json"
          }
        },
        {
          "label": "உயரம்",
          "value": {
            "label": ""
          }
        },
        {
          "label": "சொந்த நாடு",
          "value": {
            "label": "ஆஃப்கன்"
          }
        },
        {
          "label": "இவரின் பங்கு",
          "value": {
            "label": "வலதுகை லெக்ஸ்பின்"
          }
        }
      ]
    },
    {
      "title": "விளையாட்டின் பாணி",
      "id": "giqdm6qc1m9",
      "cardType": "simple",
      "facts": [
        {
          "label": "",
          "value": {
            "label": "ரஷீத் அவருடைய சகோதரர்களுடன் கிரிக்கெட் விளையாடி வளர்ந்தார், பாகிஸ்தான் ஆல்ரவுண்டர் சாஷித் அஃப்ரிடியை ரோல் மாடலாகக் கொண்ட இவர், அவருடைய பந்து வீசும் ஸ்டைலிலிருந்து தன்னுடைய ஸ்டைலை அமைத்துக் கொண்டிருக்கிறார்."
          }
        }
      ]
    },
    {
      "title": "படிநிலைகள்",
      "cardType": "vertical_timeline",
      "facts": [
        {
          "label": "முதல் வகுப்பு",
          "id": "-_kmu9OnqBb",
          "note": "",
          "value": {
            "label": ""
          }
        },
        {
          "label": "தேசிய அணி அறிமுகம்",
          "id": "SGFvs65o3vt",
          "note": "",
          "value": {
            "label": "அவர், 2015 அக்டோபர் 18 அன்று ஆப்கானிஸ்தானுக்காக ஜிம்பாப்வேக்கு எதிராகத் தன்னுடைய முதல் சர்வதேச ஒருநாள் போட்டியில் ஆடினார்."
          }
        },
        {
          "label": "முதல் ஐசிசி போட்டி ",
          "id": "A6g7M0H-J8a",
          "note": "",
          "value": {
            "label": "2019 ஏப்ரல் மாதம், 2019 உலகக் கோப்பையில் ஆப்கானிஸ்தான் அணியில் அவர் பெயர் இடம்பெற்றது."
          }
        },
        {
          "label": "2017",
          "id": "XEcam-QXEI7",
          "note": "சன்ரைசர்ஸ் ஹைதராபாத்",
          "value": {
            "label": "சன்ரைசர்ஸ் ஹைதராபாத்",
            "facts": [
              {
                "url": "/read/ta/sunrisers_hyderabad",
                "contentUrl": "/static/content/ta/sunrisers_hyderabad.json",
                "label": "Sunrisers Hyderabad",
                "id": "lvEpvWJ5DOl",
                "value": {
                  "label": "The SunRisers Hyderabad (often abbreviated as SRH) are a franchise cricket team based in Hyderabad, Telangana, that plays in the Indian Premier League (IPL)",
                  "image": {
                    "url": "/static/images/rashid_khan/Sunrisers_Hyderabad.svg",
                    "altText": "Image of Sunrisers Hyderabad"
                  }
                }
              }
            ]
          }
        }
      ]
    },
    {
      "title": "சாதனைகள்",
      "cardType": "stories",
      "facts": [
        {
          "label": "",
          "id": "achievement_or_record_1",
          "value": {
            "label": "2017 ஜூன் மாதம், சர்வதேச ஒரு நாள் கிரிக்கெட் போட்டியில் ஒரு அசோசியோட் நாட்டுக்கான சிறந்த பந்து வீச்சு புள்ளிவிவரங்களை வைத்துள்ள வீரரானார்.",
            "image": {
              "url": "",
              "altText": "2017 ஜூன் மாதம், சர்வதேச ஒரு நாள் கிரிக்கெட் போட்டியில் ஒரு அசோசியோட் நாட்டுக்கான சிறந்த பந்து வீச்சு புள்ளிவிவரங்களை வைத்துள்ள வீரரானார்."
            }
          }
        },
        {
          "label": "",
          "id": "achievement_or_record_2",
          "value": {
            "label": "2018 பிப்ரவரி மாதம், சர்வதேச ஒரு நாள் கிரிக்கெட் போட்டிகளில் பந்து வீச்சாளர்களுக்கான ஐசிசி பிளேயர் தரவரிசைப் பட்டியலில் முதல் இடம் பிடித்த இளம் வீரர்.",
            "image": {
              "url": "",
              "altText": "2018 பிப்ரவரி மாதம், சர்வதேச ஒரு நாள் கிரிக்கெட் போட்டிகளில் பந்து வீச்சாளர்களுக்கான ஐசிசி பிளேயர் தரவரிசைப் பட்டியலில் முதல் இடம் பிடித்த இளம் வீரர்."
            }
          }
        },
        {
          "label": "",
          "id": "achievement_or_record_3",
          "value": {
            "label": "2018 ஆசிய கோப்பையில் திறமையை வெளிப்படுத்தியதைத் தொடர்ந்து, செப்டம்பர் 2018 இல், ஐசிசியின் ஆல்-ரவுண்டர் தர வரிசைப்பட்டியலில் முதல் இடம் பிடித்தார்.",
            "image": {
              "url": "",
              "altText": "2018 ஆசிய கோப்பையில் திறமையை வெளிப்படுத்தியதைத் தொடர்ந்து, செப்டம்பர் 2018 இல், ஐசிசியின் ஆல்-ரவுண்டர் தர வரிசைப்பட்டியலில் முதல் இடம் பிடித்தார்."
            }
          }
        },
        {
          "label": "",
          "id": "achievement_or_record_4",
          "value": {
            "label": "",
            "image": {
              "url": "",
              "altText": ""
            }
          }
        },
        {
          "label": "",
          "id": "achievement_or_record_5",
          "value": {
            "label": "",
            "image": {
              "url": "",
              "altText": ""
            }
          }
        }
      ]
    },
    {
      "title": "அணிகள்",
      "cardType": "list_card",
      "facts": [
        {
          "label": "ஆப்கானிஸ்தான் தேசிய கிரிக்கெட் அணி (2015 முதல் தற்போது வரை)",
          "id": "TEc9z5QxDk",
          "value": {
            "label": "",
            "facts": [
              {
                "label": "Afghanistan national cricket team",
                "id": "74vdtJWSM9",
                "url": "/read/ta/afghanistan_national_cricket_team",
                "contentUrl": "/static/content/ta/afghanistan_national_cricket_team.json",
                "value": {
                  "label": "The Afghanistan national cricket team is the 12th Test cricket playing Full Member nation. Cricket has been played in Afghanistan since the mid 19th century, but it is only in recent years that the national team has become successful. ",
                  "image": {
                    "url": "/static/images/rashid_khan/Afghanistan_cricket_board_logo.jpg",
                    "altText": "Picture of Afghanistan national cricket team"
                  }
                }
              }
            ]
          }
        },
        {
          "label": "சன்ரைசர்ஸ் ஹைதராபாத் (2017 முதல் தற்போது வரை)",
          "id": "I0owVyGrR2",
          "value": {
            "label": "",
            "facts": [
              {
                "label": "Sunrisers Hyderabad",
                "id": "Y7RUm7xz3r",
                "url": "/read/ta/sunrisers_hyderabad",
                "contentUrl": "/static/content/ta/sunrisers_hyderabad.json",
                "value": {
                  "label": "The SunRisers Hyderabad (often abbreviated as SRH) are a franchise cricket team based in Hyderabad, Telangana, that plays in the Indian Premier League (IPL)",
                  "image": {
                    "url": "/static/images/rashid_khan/Sunrisers_Hyderabad.svg",
                    "altText": "Picture of Sunrisers Hyderabad"
                  }
                }
              }
            ]
          }
        }
      ]
    },
    {
      "title": "விருதுகள் & கௌரவங்கள்",
      "cardType": "tag_card",
      "facts": [
        {
          "label": "அசோசியேட் கிரிக்கெட்டர் ஆஃப் தி இயர்",
          "tag": "2018",
          "id": "award-0",
          "value": {
            "label": "",
            "image": {
              "url": "",
              "altText": "Image of அசோசியேட் கிரிக்கெட்டர் ஆஃப் தி இயர்"
            }
          }
        }
      ]
    }
  ]
}