{
  "title": "Delhi",
  "summary": "Delhi, officially the National Capital Territory of Delhi (NCT), is a city and a union territory of India containing New Delhi, the capital of India.",
  "wikipediaUrl": "https://en.wikipedia.org/wiki/Delhi",
  "coverImage": {
    "url": "/static/images/delhi/India_Gate_in_New_Delhi_03-2016.jpg",
    "altText": "Image of Delhi",
    "license": "<p>Copyleft: This work of art is free; you can redistribute it and/or modify it according to terms of the <b><a href=\"https://en.wikipedia.org/wiki/en:Free_Art_License\" class=\"extiw\" title=\"w:en:Free Art License\">Free Art License</a></b>. You will find a specimen of this license on the <a rel=\"nofollow\" class=\"external text\" href=\"http://artlibre.org/licence/lal/en/\">Copyleft Attitude site</a> as well as <a class=\"external text\" href=\"https://commons.wikimedia.org/wiki/Commons:Free_Art_License_1.3\">on other sites</a>. <span class=\"licensetpl_link\" style=\"display:none;\">http://artlibre.org/licence/lal/en</span><span class=\"licensetpl_short\" style=\"display:none;\">FAL</span><span class=\"licensetpl_long\" style=\"display:none;\">Free Art License</span><span class=\"licensetpl_link_req\" style=\"display:none;\">false</span><span class=\"licensetpl_attr_req\" style=\"display:none;\">true</span></p>"
  },
  "translations": [
    {
      "lang": "hi",
      "title": "दिल्ली",
      "url": "/read/hi/delhi"
    },
    {
      "lang": "ta",
      "title": "டெல்லி",
      "url": "/read/ta/delhi"
    }
  ],
  "sections": []
}