{
  "title": "Kane Williamson",
  "wikipediaUrl": "https://en.wikipedia.org/wiki/Kane_Williamson",
  "coverImage": {
    "url": "/static/images/master/Kane_Williamson_28977366799129.jpg",
    "altText": "Image of Kane Williamson",
    "license": "<p>This file is licensed under the <a href=\"https://en.wikipedia.org/wiki/en:Creative_Commons\" class=\"extiw\" title=\"w:en:Creative Commons\">Creative Commons</a> <a rel=\"nofollow\" class=\"external text\" href=\"https://creativecommons.org/licenses/by-sa/2.0/deed.en\">Attribution-Share Alike 2.0 Generic</a> license.</p>"
  },
  "summary": "Kane Williamson is an international cricket player from New Zealand and also the current captain of the team.",
  "translations": [
    {
      "lang": "hi",
      "title": "केन विलियमसन",
      "url": "/read/hi/kane_williamson"
    },
    {
      "lang": "ta",
      "title": "கேன் வில்லியம்சன்",
      "url": "/read/ta/kane_williamson"
    }
  ],
  "sections": [
    {
      "title": "About",
      "cardType": "table",
      "facts": [
        {
          "label": "Full Name",
          "value": {
            "label": "Kane Stuart Williamson"
          }
        },
        {
          "label": "Born on",
          "value": {
            "label": "08-08-1990 (Age 28)"
          }
        },
        {
          "label": "Birthplace",
          "value": {
            "label": "Tauranga, New Zealand",
            "url": "https://en.wikipedia.org/wiki/Tauranga",
            "contentUrl": "/static/content/en/tauranga.json"
          }
        },
        {
          "label": "Height",
          "value": {
            "label": "5 ft 9 in (1.75 m)"
          }
        },
        {
          "label": "Nationality",
          "value": {
            "label": "New Zealander"
          }
        },
        {
          "label": "Role",
          "value": {
            "label": "Batsman"
          }
        }
      ]
    },
    {
      "title": "Education",
      "cardType": "avatar",
      "facts": [
        {
          "label": "Tauranga Boys' College",
          "value": {
            "label": "Williamson scored 40 centuries before he left school.",
            "image": {
              "url": "/static/images/master/Tbc_crest.png",
              "altText": "Image of Tauranga Boys' College"
            }
          }
        }
      ]
    },
    {
      "title": "Style of Play",
      "id": "style_of_play",
      "cardType": "simple",
      "facts": [
        {
          "label": "",
          "value": {
            "label": "Right-handed batsman and an occasional off spin bowler.",
            "image": {
              "url": "/static/images/master/Kane_Williamson_28977366799129.jpg",
              "altText": "Style of play for Kane Williamson",
              "license": "<p>This file is licensed under the <a href=\"https://en.wikipedia.org/wiki/en:Creative_Commons\" class=\"extiw\" title=\"w:en:Creative Commons\">Creative Commons</a> <a rel=\"nofollow\" class=\"external text\" href=\"https://creativecommons.org/licenses/by-sa/2.0/deed.en\">Attribution-Share Alike 2.0 Generic</a> license.</p>"
            }
          }
        }
      ]
    },
    {
      "title": "Phases",
      "cardType": "vertical_timeline",
      "facts": [
        {
          "label": "First class Debut",
          "id": "phase_first_class_debut",
          "note": "2007",
          "value": {
            "label": "Williamson made his first-class cricket debut in December 2007"
          }
        },
        {
          "label": "National team debut ",
          "id": "phase_national_team_debut",
          "note": "2010",
          "value": {
            "label": "Williamson made his One-Day International debut against India, and was dismissed for a duck.",
            "facts": [
              {
                "url": "/read/en/india_national_cricket_team",
                "contentUrl": "/static/content/en/india_national_cricket_team.json",
                "label": "India national cricket team",
                "id": "phase_fact_fact_india_national_cricket_team",
                "value": {
                  "label": "The India national cricket team is also known as Team India and Men in Blue. India is ranked first in Tests, second in ODIs and second in T20Is by the ICC. Virat Kohli is the current captain of the team, while the head coach is Ravi Shastri.",
                  "image": {
                    "url": "/static/images/master/Flagcricket.jpg",
                    "altText": "Image of India national cricket team"
                  }
                }
              }
            ]
          }
        },
        {
          "label": "ICC Tournament Debut",
          "id": "phase_icc_tournament_debut",
          "note": "2011",
          "value": {
            "label": ""
          }
        },
        {
          "label": "T20 World cup",
          "id": "phase_t20_world_cup",
          "note": "2012",
          "value": {
            "label": "",
            "facts": [
              {
                "url": "/read/en/icc_t20_world_cup",
                "contentUrl": "/static/content/en/icc_t20_world_cup.json",
                "label": "ICC T20 World Cup",
                "id": "phase_fact_fact_icc_t20_world_cup",
                "value": {
                  "label": "The ICC T20 World Cup (earlier known as ICC World Twenty20) is the international championship of Twenty20 International cricket. The tournament currently consists of 16 teams, comprising the top eight teams from the rankings at the given deadline and four other teams chosen through the T20 World Cup Qualifier. ",
                  "image": {
                    "url": "/static/images/master/ICC_World_Twenty20_Trophy.jpg",
                    "altText": "Image of ICC T20 World Cup"
                  }
                }
              }
            ]
          }
        },
        {
          "label": "IPL Debut",
          "id": "phase_ipl_debut",
          "note": "2016",
          "value": {
            "label": "In 2015 Sunrisers Hyderabad of the IPL signed Williamson for US$96,500. He played for Sunrisers Hyderabad in the 2016 season where they won the title",
            "facts": [
              {
                "url": "/read/en/sunrisers_hyderabad",
                "contentUrl": "/static/content/en/sunrisers_hyderabad.json",
                "label": "Sunrisers Hyderabad",
                "id": "phase_fact_fact_sunrisers_hyderabad",
                "value": {
                  "label": "The SunRisers Hyderabad (often abbreviated as SRH) are a franchise cricket team based in Hyderabad, Telangana, that plays in the Indian Premier League (IPL).",
                  "image": {
                    "url": "/static/images/master/Sunrisers_Hyderabad.svg",
                    "altText": "Image of Sunrisers Hyderabad"
                  }
                }
              }
            ]
          }
        }
      ]
    },
    {
      "title": "Achievement & Records",
      "cardType": "stories",
      "facts": [
        {
          "label": "",
          "id": "achievement_or_record_1",
          "value": {
            "label": "In 2015, Williamson scored 2692 runs which is the highest score across all forms of international cricket for the year",
            "image": {
              "url": "/static/images/master/Kane_Williamson_28968585569729.jpg",
              "altText": "In 2015, Williamson scored 2692 runs which is the highest score across all forms of international cricket for the year",
              "license": "<p>This file is licensed under the <a href=\"https://en.wikipedia.org/wiki/en:Creative_Commons\" class=\"extiw\" title=\"w:en:Creative Commons\">Creative Commons</a> <a rel=\"nofollow\" class=\"external text\" href=\"https://creativecommons.org/licenses/by-sa/2.0/deed.en\">Attribution-Share Alike 2.0 Generic</a> license.</p>"
            }
          }
        },
        {
          "label": "",
          "id": "achievement_or_record_2",
          "value": {
            "label": "In 2016, Williamson became the 13th batsman to score a century against all the other Test playing nations",
            "image": {
              "url": "/static/images/master/Kane_Williamson_28977366799129.jpg",
              "altText": "In 2016, Williamson became the 13th batsman to score a century against all the other Test playing nations",
              "license": "<p>This file is licensed under the <a href=\"https://en.wikipedia.org/wiki/en:Creative_Commons\" class=\"extiw\" title=\"w:en:Creative Commons\">Creative Commons</a> <a rel=\"nofollow\" class=\"external text\" href=\"https://creativecommons.org/licenses/by-sa/2.0/deed.en\">Attribution-Share Alike 2.0 Generic</a> license.</p>"
            }
          }
        },
        {
          "label": "",
          "id": "achievement_or_record_3",
          "value": {
            "label": "Williamson in the youngest century scorer in New Zealand's cricket history",
            "image": {
              "url": "",
              "altText": "Williamson in the youngest century scorer in New Zealand's cricket history"
            }
          }
        },
        {
          "label": "",
          "id": "achievement_or_record_4",
          "value": {
            "label": "Williamson has scored a century in this Test debut",
            "image": {
              "url": "",
              "altText": "Williamson has scored a century in this Test debut"
            }
          }
        },
        {
          "label": "",
          "id": "achievement_or_record_5",
          "value": {
            "label": "In 2015, Williamson scored over 700 runs in the first two months of the calendar year.",
            "image": {
              "url": "",
              "altText": "In 2015, Williamson scored over 700 runs in the first two months of the calendar year."
            }
          }
        }
      ]
    },
    {
      "title": "Teams",
      "cardType": "list_card",
      "facts": [
        {
          "label": "New Zealand National Cricket team (2010 - present)",
          "id": "team_fact_new_zealand_national_cricket_team_2010 - present",
          "value": {
            "label": "",
            "facts": [
              {
                "label": "New Zealand national cricket team",
                "id": "team_fact_fact_new_zealand_national_cricket_team",
                "url": "/read/en/new_zealand_national_cricket_team",
                "contentUrl": "/static/content/en/new_zealand_national_cricket_team.json",
                "value": {
                  "label": "The New Zealand national cricket team, nicknamed the Black Caps, played their first Test in 1930 against England in Christchurch, becoming the fifth country to play Test cricket. ",
                  "image": {
                    "url": "/static/images/master/New_Zealand_Cricket_Cap_Insignia.svg",
                    "altText": "Picture of New Zealand national cricket team"
                  }
                }
              }
            ]
          }
        },
        {
          "label": "Sunrisers Hyderabad (2015 - present)",
          "id": "team_fact_sunrisers_hyderabad_2015 - present",
          "value": {
            "label": "",
            "facts": [
              {
                "label": "Sunrisers Hyderabad",
                "id": "team_fact_fact_sunrisers_hyderabad",
                "url": "/read/en/sunrisers_hyderabad",
                "contentUrl": "/static/content/en/sunrisers_hyderabad.json",
                "value": {
                  "label": "The SunRisers Hyderabad (often abbreviated as SRH) are a franchise cricket team based in Hyderabad, Telangana, that plays in the Indian Premier League (IPL).",
                  "image": {
                    "url": "/static/images/master/Sunrisers_Hyderabad.svg",
                    "altText": "Picture of Sunrisers Hyderabad"
                  }
                }
              }
            ]
          }
        },
        {
          "label": "Northern Districts (2007 - present)",
          "id": "team_fact_northern_districts_2007 - present",
          "value": {
            "label": "Northern Districts cricket team is a first-class cricket team from New Zealand."
          }
        }
      ]
    },
    {
      "title": "Awards & Honors",
      "cardType": "tag_card",
      "facts": [
        {
          "label": "Halberg Award",
          "tag": "2015",
          "id": "award-0",
          "value": {
            "label": "Halberg Awards are given annually to New Zealand's top sportperson.",
            "image": {
              "url": "",
              "altText": "Image of Halberg Award"
            }
          }
        },
        {
          "label": "Wisden Leading Cricketer of the World",
          "tag": "2015",
          "id": "award-1",
          "value": {
            "label": "Wisden Leading Cricketer in the World is an annual cricket award selected by Wisden Cricketers' Almanack",
            "image": {
              "url": "",
              "altText": "Image of Wisden Leading Cricketer of the World"
            }
          }
        }
      ]
    }
  ],
  "category": "personality"
}