{
  "title": "अनिल कुंबले",
  "wikipediaUrl": "https://en.wikipedia.org/wiki/Anil_Kumble",
  "coverImage": {
    "url": "https://commons.wikimedia.org/wiki/File:Anil_Kumble.jpg",
    "altText": "Image of अनिल कुंबले"
  },
  "summary": "अनिल कुंबले भारत के एक पूर्व क्रिकेटर और टेस्ट तथा अन्‍तर्राष्ट्रीय एक दिवसीय मैचों (वनडे) के पूर्व कप्तान रहे हैं, जिन्होंने 18 वर्षों तक टेस्ट और अन्‍तर्राष्ट्रीय एकदिवसीय मैच खेले।",
  "translations": [
    {
      "lang": "en",
      "title": "Anil Kumble",
      "url": "/read/en/anil_kumble"
    },
    {
      "lang": "ta",
      "title": "அனில் கும்ப்ளே",
      "url": "/read/ta/anil_kumble"
    }
  ],
  "sections": [
    {
      "title": "About",
      "cardType": "table",
      "facts": [
        {
          "label": "Full Name",
          "value": {
            "label": "अनिल कुंबले "
          }
        },
        {
          "label": "Born On",
          "value": {
            "label": "17 Oct 1970 (age 48)"
          }
        },
        {
          "label": "Birthplace",
          "value": {
            "label": "बेंगलुरु, भारत",
            "url": "https://en.wikipedia.org/wiki/Bangalore",
            "contentUrl": "/static/content/hi/bangalore.json"
          }
        },
        {
          "label": "Height",
          "value": {
            "label": "6 फीट 1 इंच (1.85 मीटर)"
          }
        },
        {
          "label": "Other Names",
          "value": {
            "label": "जम्बो "
          }
        },
        {
          "label": "Nationality",
          "value": {
            "label": "भारतीय"
          }
        },
        {
          "label": "Role",
          "value": {
            "label": "लेग स्पिन गेंदबाज"
          }
        }
      ]
    },
    {
      "title": "Alma mater",
      "cardType": "avatar",
      "facts": [
        {
          "label": "राष्ट्रीय विद्यालय कॉलेज ऑफ इंजीनियरिंग",
          "value": {
            "label": "",
            "image": {
              "url": "/static/images/default_person.svg",
              "altText": "Image of राष्ट्रीय विद्यालय कॉलेज ऑफ इंजीनियरिंग"
            }
          }
        }
      ]
    },
    {
      "title": "Style of play",
      "id": "ok8aB41ow16",
      "cardType": "simple",
      "facts": [
        {
          "label": "",
          "value": {
            "label": "कुंबले अपरंपरागत शैली के दाएं हाथ के लेग स्पिनर (लेगब्रेक गुगली) हैं, जो अपने फ़्लिपर के लिए सबसे ज्यादा प्रसिद्ध हैं और दाहिने हाथ के बल्लेबाज हैं। उन्होंने अपने करियर की शुरुआत एक तेज़ गेंदबाज़ के रूप में की,  जिससे उन्हें एक उपयोगी तेज़ गेंद डालने की प्रतिभा प्राप्त हुई। उनकी अनूठी गेंदबाजी शैली का श्रेय बेंगलोर की मैटिंग पिचों को दिया जा सकता है जो उन्‍हें टॉप-स्पिन और ओवर-स्पिन कराने में मददगार रहे। ",
            "image": {
              "url": "https://upload.wikimedia.org/wikipedia/commons/0/09/GandM_Flare_DXM_bat-Purist_156g_ball.jpg",
              "altText": "Style of play for अनिल कुंबले"
            }
          }
        }
      ]
    },
    {
      "title": "Phase(s)",
      "cardType": "vertical_timeline",
      "facts": [
        {
          "label": "प्रथम श्रेणी की शुरुआत",
          "id": "Uz328MbMBVQ",
          "note": "1989",
          "value": {
            "label": "कुंबले ने हैदराबाद के खिलाफ कर्नाटक की ओर से प्रथम श्रेणी  क्रिकेट में 30 नवंबर 1989 को पदार्पण किया और इस मैच उन्होंने 4 विकेट प्राप्त किया। "
          }
        },
        {
          "label": "राष्ट्रीय टीम ",
          "id": "NgeCb4_uukC",
          "note": "1990",
          "value": {
            "label": "कुंबले ने 1990 में आस्ट्रेलेशिया कप में सारजाह में श्रीलंका के विरुद्ध वनडे इंटरनेशनल में पदार्पण किया। "
          }
        },
        {
          "label": "विश्व कप",
          "id": "NBMKRxboiC9",
          "note": "1996",
          "value": {
            "label": "1996 के विश्व कप के लिए कुंबले का चयन भारतीय टीम में हुआ और वे इस टुर्नामेंट में सबसे ज्यादा विकेट प्राप्त करने वाले गेंदबाजों में से एक रहे। ",
            "facts": [
              {
                "url": "/read/hi/1996_cricket_world_cup",
                "contentUrl": "/static/content/hi/1996_cricket_world_cup.json",
                "label": "1996 क्रिकेट विश्व कप",
                "id": "6m9eQS83HwO",
                "value": {
                  "label": "1996 क्रिकेट विश्व कप, जिसे उसके आधिकारिक प्रायोजकों (आईटीसी के विल्स ब्रांड) के नाम पर, विल्स वर्ल्ड कप 1996 भी कहा जाता है, छठा क्रिकेट विश्व कप था। यह पाकिस्तान और भारत द्वारा आयोजित होने वाला दूसरा, और श्रीलंका आयोजित होने वाला पहला विश्व कप था।",
                  "image": {
                    "url": "https://en.wikipedia.org/wiki/1996_Cricket_World_Cup#/media/File:Wills_World_Cup_1996.svg",
                    "altText": "Image of 1996 क्रिकेट विश्व कप"
                  }
                }
              }
            ]
          }
        },
        {
          "label": "संन्यास",
          "id": "uVBrg3DvQZz",
          "note": "2007",
          "value": {
            "label": "2007 के विश्व कप के बाद उन्होंने वनडे इंटरनेशनल से संन्यास लेने की घोषणा कर दी। "
          }
        },
        {
          "label": "IPL डेब्यू",
          "id": "QnQeB7xGUpD",
          "note": "2008",
          "value": {
            "label": "रॉयल चैलेंजर्स बंगलुरु के अनुबंध के प्रति सम्मान दिखाते हुए कुंबले ने संन्यास के बाद 3 वर्ष तक इस टीम के लिए खेलना जारी रखा। "
          }
        }
      ]
    },
    {
      "title": "Achievements & Records",
      "cardType": "stories",
      "facts": [
        {
          "label": "",
          "id": "achievement_or_record_1",
          "value": {
            "label": "कुंबले ऐसे दूसरे खिलाड़ी हैं जिन्होंने एक टेस्ट मैच की एक पारी में सभी 10 विकेट लिए हैं।",
            "image": {
              "url": "",
              "altText": "कुंबले ऐसे दूसरे खिलाड़ी हैं जिन्होंने एक टेस्ट मैच की एक पारी में सभी 10 विकेट लिए हैं।"
            }
          }
        },
        {
          "label": "",
          "id": "achievement_or_record_2",
          "value": {
            "label": "कुंबले ने 1996 में 61 विकेट के साथ किसी भी भारतीय क्रिकेटर द्वारा एक कैलेंडर वर्ष में सर्वाधिक विकेट लेने का रिकॉर्ड बनाया",
            "image": {
              "url": "",
              "altText": "कुंबले ने 1996 में 61 विकेट के साथ किसी भी भारतीय क्रिकेटर द्वारा एक कैलेंडर वर्ष में सर्वाधिक विकेट लेने का रिकॉर्ड बनाया"
            }
          }
        },
        {
          "label": "",
          "id": "achievement_or_record_3",
          "value": {
            "label": "कुंबले के नाम अपने पूरे टेस्ट करियर के दौरान 40850 गेंदे करने का रिकॉर्ड है, जो किसी भी भारतीय का सर्वाधिक है।",
            "image": {
              "url": "",
              "altText": "कुंबले के नाम अपने पूरे टेस्ट करियर के दौरान 40850 गेंदे करने का रिकॉर्ड है, जो किसी भी भारतीय का सर्वाधिक है।"
            }
          }
        },
        {
          "label": "",
          "id": "achievement_or_record_4",
          "value": {
            "label": "कुंबले ने अपने पहले 50 टेस्ट विकेट 10 मैचों में लिए",
            "image": {
              "url": "",
              "altText": "कुंबले ने अपने पहले 50 टेस्ट विकेट 10 मैचों में लिए"
            }
          }
        },
        {
          "label": "",
          "id": "achievement_or_record_5",
          "value": {
            "label": "1993 में, इन्होंने वेस्टइंडीज के खिलाफ एक वनडे मैच में 12 रन देकर छह विकेट लिए जो बहुत लंबे समय तक एक भारतीय रिकॉर्ड बना रहा।",
            "image": {
              "url": "",
              "altText": "1993 में, इन्होंने वेस्टइंडीज के खिलाफ एक वनडे मैच में 12 रन देकर छह विकेट लिए जो बहुत लंबे समय तक एक भारतीय रिकॉर्ड बना रहा।"
            }
          }
        }
      ]
    },
    {
      "title": "Team(s)",
      "cardType": "list_card",
      "facts": [
        {
          "label": "भारतीय राष्ट्रीय क्रिकेट टीम (1990-2008)",
          "id": "HJ7z6mje1Xm",
          "value": {
            "label": "भारत की राष्ट्रीय क्रिकेट टीम, जिसे टीम इंडिया और मैन इन ब्लू के नाम से भी जाना जाता है, भारतीय क्रिकेट कंट्रोल बोर्ड द्वारा संचालित है"
          }
        },
        {
          "label": "रॉयल चैलेंजर्स बेंगलोर (2008-2010)",
          "id": "qVoU77VD3I9",
          "value": {
            "label": "रॉयल चैलेंजर्स बैंगलोर (आरसीबी) बेंगलोर, भारत की एक फ्रैंचाइज़ी क्रिकेट टीम है।"
          }
        },
        {
          "label": "कर्नाटक (1989-2009)",
          "id": "pgPQ9my-G9l",
          "value": {
            "label": "कर्नाटक राज्य की घरेलू रणजी ट्रॉफी क्रिकेट टीम "
          }
        }
      ]
    }
  ]
}